dpt_cache/__init__.py
dpt_cache/abstract_file_content.py
dpt_cache/abstract_vfs_content.py
dpt_cache/content.py
dpt_cache/file_content.py
dpt_cache/json_file_content.py
dpt_cache-1.0.2.data/data/docs/LICENSE
dpt_cache-1.0.2.data/data/docs/README
dpt_cache-1.0.2.dist-info/LICENSE
dpt_cache-1.0.2.dist-info/METADATA
dpt_cache-1.0.2.dist-info/WHEEL
dpt_cache-1.0.2.dist-info/top_level.txt
dpt_cache-1.0.2.dist-info/RECORD
