Metadata-Version: 2.1
Name: dpt-cache
Version: 1.0.2
Summary: Extendible data and virtual filesystem timestamp based caching solution
Home-page: https://www.direct-netware.de/redirect?dpt;cache
Author: direct Netware Group et al.
Author-email: web@direct-netware.de
License: MPL2
Platform: any
Classifier: Intended Audience :: Developers
Classifier: License :: OSI Approved :: Mozilla Public License 2.0 (MPL 2.0)
Classifier: Operating System :: OS Independent
Classifier: Programming Language :: Python
Classifier: Topic :: Software Development :: Libraries :: Python Modules
Requires-Dist: dpt-file (<2,>=1)
Requires-Dist: dpt-json (<2,>=1)
Requires-Dist: dpt-logging (<2,>=1.1.0)
Requires-Dist: dpt-module-loader (<2,>=1)
Requires-Dist: dpt-runtime (<3,>=2)
Requires-Dist: dpt-settings (<2,>=1)
Requires-Dist: dpt-threading (<3,>=2)
Requires-Dist: dpt-vfs (<2,>=1)
